musicai_sdk/__init__.py
musicai_sdk/client.py
musicai_sdk/utils.py
musicai_sdk-1.0.3.dist-info/METADATA
musicai_sdk-1.0.3.dist-info/WHEEL
musicai_sdk-1.0.3.dist-info/RECORD
