Metadata-Version: 2.3
Name: musicai-sdk
Version: 1.0.3
Summary: Python SDK for Music.AI
License: MIT
Author: Music.ai Support
Author-email: support@music.ai
Requires-Python: >=3.8,<4.0
Classifier: License :: OSI Approved :: MIT License
Classifier: Programming Language :: Python :: 3
Classifier: Programming Language :: Python :: 3.8
Classifier: Programming Language :: Python :: 3.9
Classifier: Programming Language :: Python :: 3.10
Classifier: Programming Language :: Python :: 3.11
Classifier: Programming Language :: Python :: 3.12
Classifier: Programming Language :: Python :: 3.13
Requires-Dist: requests (>=2.31.0,<3.0.0)
